nana.py
nana-1.0.6.dist-info/DESCRIPTION.rst
nana-1.0.6.dist-info/METADATA
nana-1.0.6.dist-info/RECORD
nana-1.0.6.dist-info/WHEEL
nana-1.0.6.dist-info/entry_points.txt
nana-1.0.6.dist-info/metadata.json
nana-1.0.6.dist-info/top_level.txt
